janus_ssmm_tlm_info/__init__.py
janus_ssmm_tlm_info/cli.py
janus_ssmm_tlm_info/janus_pkt.py
janus_ssmm_tlm_info/packets.py
janus_ssmm_tlm_info/py.typed
janus_ssmm_tlm_info/time.py
janus_ssmm_tlm_info-0.0.8.dist-info/METADATA
janus_ssmm_tlm_info-0.0.8.dist-info/WHEEL
janus_ssmm_tlm_info-0.0.8.dist-info/entry_points.txt
janus_ssmm_tlm_info-0.0.8.dist-info/licenses/LICENSE
janus_ssmm_tlm_info-0.0.8.dist-info/RECORD
