Metadata-Version: 2.4
Name: janus-ssmm-tlm-info
Version: 0.0.8
Summary: Provides information on JANUS SSMM images content.
Project-URL: documentation, https://JANUS-JUICE.github.io/janus-ssmm-tlm-info
Project-URL: homepage, https://JANUS-JUICE.github.io/janus-ssmm-tlm-info
Project-URL: repository, https://github.com/JANUS-JUICE/janus-ssmm-tlm-info
Author-email: Luca Penasa <luca.penasa@inaf.it>
License-Expression: MIT
License-File: LICENSE
Classifier: Development Status :: 4 - Beta
Classifier: Intended Audience :: Developers
Classifier: Operating System :: OS Independent
Classifier: Programming Language :: Python
Classifier: Programming Language :: Python :: 3
Classifier: Programming Language :: Python :: 3.10
Classifier: Programming Language :: Python :: 3.11
Classifier: Programming Language :: Python :: 3.12
Classifier: Programming Language :: Python :: 3.13
Classifier: Topic :: Software Development :: Libraries :: Python Modules
Classifier: Typing :: Typed
Requires-Python: <4.0,>=3.10
Requires-Dist: click>=8.1.7
Requires-Dist: construct>=2.10.70
Requires-Dist: importlib-metadata<9,>=8.5.0
Requires-Dist: loguru>=0.7.2
Requires-Dist: spiceypy>=6.0.0
